{
    "infos": [
        {
            "edl_etat_edl_lot_designation": "Appartement",
            "edl_etat_etat": "edl_etat_etat_ferme",
            "edl_etat_date_signature": "",
            "edl_etat_edl_lot_adresse_ligne_1": "18 Rue du Mont-Blanc\n",
            "edl_etat_edl_lot_adresse_ligne_2": "",
            "edl_etat_edl_lot_ville": "Sallanches",
            "edl_etat_edl_lot_code_postal": "74700",
            "edl_etat_edl_lot_type_bien": "Appartement",
            "edl_etat_edl_lot_nb_room": "1",
            "edl_etat_edl_lot_lot_meuble": "",
            "edl_etat_edl_lot_num_etage": ": 3\u00e8me",
            "edl_etat_edl_lot_num_appart": ": ET3G",
            "edl_etat_edl_lot_description_logement": "",
            "edl_etat_edl_lot_code_acces_immeuble": "",
            "edl_etat_edl_lot_surface_habitable": ": 30,10",
            "edl_etat_nom_representant": "",
            "edl_etat_email_representant": "",
            "edl_etat_phone_representant": ""
        }
    ],
    "owners": [
        {
            "edl_etat_owner_last_name": ": SCI C2P"
        }
    ],
    "occupants": [
        {
            "edl_etat_occupant_last_name": "Amelia FISSEAU",
            "edl_etat_occupant_address_1": "",
            "edl_etat_occupant_address_2": "",
            "edl_etat_occupant_zip_code": "",
            "edl_etat_occupant_city": "",
            "edl_etat_occupant_telephone": "",
            "edl_etat_occupant_mobile": "",
            "edl_etat_occupant_email": "",
            "edl_etat_occupant_entry_date": "9 septembre 2015"
        }
    ],
    "room": [
        {
            "edl_etat_element_intitule": "Entr\u00e9e",
            "edl_etat_element_type": 1,
            "edl_etat_element_valeur": "",
            "edl_etat_element_observations": "",
            "element": []
        },
        {
            "edl_etat_element_intitule": "Cuisine",
            "edl_etat_element_type": 1,
            "edl_etat_element_valeur": "",
            "edl_etat_element_observations": "",
            "element": [
                {
                    "edl_etat_element_intitule": "vue g\u00e9n\u00e9rale",
                    "edl_etat_element_type": 1,
                    "edl_etat_element_valeur": "",
                    "edl_etat_element_observations": "",
                    "elements": [],
                    "photos": [
                        {
                            "edl_photo_intitule": "Photo 3, 4, 5",
                            "edl_photo_commentaire": "vue g\u00e9n\u00e9rale",
                            "edl_photo_data_uri": ""
                        }
                    ]
                },
                {
                    "edl_etat_element_intitule": "Sol",
                    "edl_etat_element_type": 1,
                    "edl_etat_element_valeur": "",
                    "edl_etat_element_observations": "",
                    "elements": [
                        {
                            "edl_etat_element_intitule": "Description",
                            "edl_etat_element_type": 2,
                            "edl_etat_element_valeur": "linol\u00e9um",
                            "edl_etat_element_observations": ""
                        },
                        {
                            "edl_etat_element_intitule": "Etat",
                            "edl_etat_element_type": 2,
                            "edl_etat_element_valeur": "d'usage",
                            "edl_etat_element_observations": ""
                        }
                    ],
                    "photos": [
                        {
                            "edl_photo_intitule": "Photo 6, 7, 8",
                            "edl_photo_commentaire": " Etat d'usage",
                            "edl_photo_data_uri": ""
                        }
                    ]
                },
                {
                    "edl_etat_element_intitule": "Plinthes",
                    "edl_etat_element_type": 1,
                    "edl_etat_element_valeur": "",
                    "edl_etat_element_observations": "",
                    "elements": [
                        {
                            "edl_etat_element_intitule": "Nature",
                            "edl_etat_element_type": 2,
                            "edl_etat_element_valeur": "bois",
                            "edl_etat_element_observations": ""
                        },
                        {
                            "edl_etat_element_intitule": "Etat",
                            "edl_etat_element_type": 2,
                            "edl_etat_element_valeur": "d'usage",
                            "edl_etat_element_observations": ""
                        }
                    ],
                    "photos": [
                        {
                            "edl_photo_intitule": "Photo 9, 10",
                            "edl_photo_commentaire": " Etat d'usage",
                            "edl_photo_data_uri": ""
                        }
                    ]
                },
                {
                    "edl_etat_element_intitule": "Murs",
                    "edl_etat_element_type": 1,
                    "edl_etat_element_valeur": "",
                    "edl_etat_element_observations": "",
                    "elements": [
                        {
                            "edl_etat_element_intitule": "Nature",
                            "edl_etat_element_type": 2,
                            "edl_etat_element_valeur": "cr\u00e9pis",
                            "edl_etat_element_observations": ""
                        },
                        {
                            "edl_etat_element_intitule": "Description",
                            "edl_etat_element_type": 2,
                            "edl_etat_element_valeur": "Tache (photo 11, 12, 13)\n",
                            "edl_etat_element_observations": ""
                        },
                        {
                            "edl_etat_element_intitule": "Description",
                            "edl_etat_element_type": 2,
                            "edl_etat_element_valeur": "Fissure (photo 14, 15, 16)\n",
                            "edl_etat_element_observations": ""
                        }
                    ],
                    "photos": [
                        {
                            "edl_photo_intitule": "Photo 11, 12, 13",
                            "edl_photo_commentaire": " Tache",
                            "edl_photo_data_uri": ""
                        },
                        {
                            "edl_photo_intitule": "Photo 14, 15, 16",
                            "edl_photo_commentaire": " Fissure",
                            "edl_photo_data_uri": ""
                        }
                    ]
                },
                {
                    "edl_etat_element_intitule": "Radiateur",
                    "edl_etat_element_type": 1,
                    "edl_etat_element_valeur": "",
                    "edl_etat_element_observations": "",
                    "elements": [
                        {
                            "edl_etat_element_intitule": "Description",
                            "edl_etat_element_type": 2,
                            "edl_etat_element_valeur": "\u00e9lectrique",
                            "edl_etat_element_observations": ""
                        },
                        {
                            "edl_etat_element_intitule": "Etat",
                            "edl_etat_element_type": 2,
                            "edl_etat_element_valeur": "Bon",
                            "edl_etat_element_observations": ""
                        }
                    ],
                    "photos": [
                        {
                            "edl_photo_intitule": "Photo 17",
                            "edl_photo_commentaire": " Bon \u00e9tat",
                            "edl_photo_data_uri": ""
                        }
                    ]
                },
                {
                    "edl_etat_element_intitule": "Point lumineux",
                    "edl_etat_element_type": 1,
                    "edl_etat_element_valeur": "",
                    "edl_etat_element_observations": "",
                    "elements": [
                        {
                            "edl_etat_element_intitule": "Description",
                            "edl_etat_element_type": 2,
                            "edl_etat_element_valeur": "applique",
                            "edl_etat_element_observations": ""
                        },
                        {
                            "edl_etat_element_intitule": "Etat",
                            "edl_etat_element_type": 2,
                            "edl_etat_element_valeur": "Bon",
                            "edl_etat_element_observations": ""
                        }
                    ],
                    "photos": [
                        {
                            "edl_photo_intitule": "Photo 18, 19",
                            "edl_photo_commentaire": " Bon \u00e9tat",
                            "edl_photo_data_uri": ""
                        }
                    ]
                },
                {
                    "edl_etat_element_intitule": "Frigo",
                    "edl_etat_element_type": 1,
                    "edl_etat_element_valeur": "",
                    "edl_etat_element_observations": "",
                    "elements": [],
                    "photos": []
                },
                {
                    "edl_etat_element_intitule": "cong\u00e9lateur",
                    "edl_etat_element_type": 1,
                    "edl_etat_element_valeur": "",
                    "edl_etat_element_observations": "",
                    "elements": [
                        {
                            "edl_etat_element_intitule": "Description",
                            "edl_etat_element_type": 2,
                            "edl_etat_element_valeur": "classique",
                            "edl_etat_element_observations": ""
                        },
                        {
                            "edl_etat_element_intitule": "Etat",
                            "edl_etat_element_type": 2,
                            "edl_etat_element_valeur": "Bon",
                            "edl_etat_element_observations": ""
                        }
                    ],
                    "photos": [
                        {
                            "edl_photo_intitule": "Photo 20, 21",
                            "edl_photo_commentaire": " Bon \u00e9tat",
                            "edl_photo_data_uri": ""
                        }
                    ]
                },
                {
                    "edl_etat_element_intitule": "Cuisini\u00e8re",
                    "edl_etat_element_type": 1,
                    "edl_etat_element_valeur": "",
                    "edl_etat_element_observations": "",
                    "elements": [
                        {
                            "edl_etat_element_intitule": "Description",
                            "edl_etat_element_type": 2,
                            "edl_etat_element_valeur": "\u00e9lectrique",
                            "edl_etat_element_observations": ""
                        },
                        {
                            "edl_etat_element_intitule": "Etat",
                            "edl_etat_element_type": 2,
                            "edl_etat_element_valeur": "Bon",
                            "edl_etat_element_observations": ""
                        }
                    ],
                    "photos": [
                        {
                            "edl_photo_intitule": "Photo 22",
                            "edl_photo_commentaire": " Bon \u00e9tat",
                            "edl_photo_data_uri": ""
                        }
                    ]
                },
                {
                    "edl_etat_element_intitule": "Hotte aspirante",
                    "edl_etat_element_type": 1,
                    "edl_etat_element_valeur": "",
                    "edl_etat_element_observations": "",
                    "elements": [
                        {
                            "edl_etat_element_intitule": "Description",
                            "edl_etat_element_type": 2,
                            "edl_etat_element_valeur": "Whirlpool",
                            "edl_etat_element_observations": ""
                        },
                        {
                            "edl_etat_element_intitule": "Etat",
                            "edl_etat_element_type": 2,
                            "edl_etat_element_valeur": "Bon",
                            "edl_etat_element_observations": ""
                        }
                    ],
                    "photos": [
                        {
                            "edl_photo_intitule": "Photo 23",
                            "edl_photo_commentaire": " Bon \u00e9tat",
                            "edl_photo_data_uri": ""
                        }
                    ]
                },
                {
                    "edl_etat_element_intitule": "Meubles",
                    "edl_etat_element_type": 1,
                    "edl_etat_element_valeur": "",
                    "edl_etat_element_observations": "",
                    "elements": [
                        {
                            "edl_etat_element_intitule": "Description",
                            "edl_etat_element_type": 2,
                            "edl_etat_element_valeur": "m\u00e9lamin\u00e9",
                            "edl_etat_element_observations": ""
                        },
                        {
                            "edl_etat_element_intitule": "Etat",
                            "edl_etat_element_type": 2,
                            "edl_etat_element_valeur": "Bon",
                            "edl_etat_element_observations": ""
                        }
                    ],
                    "photos": [
                        {
                            "edl_photo_intitule": "Photo 24, 25, 26",
                            "edl_photo_commentaire": " Bon \u00e9tat",
                            "edl_photo_data_uri": ""
                        }
                    ]
                },
                {
                    "edl_etat_element_intitule": "Fen\u00eatre",
                    "edl_etat_element_type": 1,
                    "edl_etat_element_valeur": "",
                    "edl_etat_element_observations": "",
                    "elements": [
                        {
                            "edl_etat_element_intitule": "Description",
                            "edl_etat_element_type": 2,
                            "edl_etat_element_valeur": "type velux",
                            "edl_etat_element_observations": ""
                        },
                        {
                            "edl_etat_element_intitule": "Etat",
                            "edl_etat_element_type": 2,
                            "edl_etat_element_valeur": "Bon",
                            "edl_etat_element_observations": ""
                        }
                    ],
                    "photos": [
                        {
                            "edl_photo_intitule": "Photo 27",
                            "edl_photo_commentaire": " Bon \u00e9tat",
                            "edl_photo_data_uri": ""
                        }
                    ]
                },
                {
                    "edl_etat_element_intitule": "Stores",
                    "edl_etat_element_type": 1,
                    "edl_etat_element_valeur": "",
                    "edl_etat_element_observations": "",
                    "elements": [
                        {
                            "edl_etat_element_intitule": "Description",
                            "edl_etat_element_type": 2,
                            "edl_etat_element_valeur": "volets roulants",
                            "edl_etat_element_observations": ""
                        },
                        {
                            "edl_etat_element_intitule": "Etat",
                            "edl_etat_element_type": 2,
                            "edl_etat_element_valeur": "Bon",
                            "edl_etat_element_observations": ""
                        }
                    ],
                    "photos": [
                        {
                            "edl_photo_intitule": "Photo 28",
                            "edl_photo_commentaire": " Bon \u00e9tat",
                            "edl_photo_data_uri": ""
                        }
                    ]
                },
                {
                    "edl_etat_element_intitule": "Plafond",
                    "edl_etat_element_type": 1,
                    "edl_etat_element_valeur": "",
                    "edl_etat_element_observations": "",
                    "elements": [
                        {
                            "edl_etat_element_intitule": "Nature",
                            "edl_etat_element_type": 2,
                            "edl_etat_element_valeur": "cr\u00e9pi",
                            "edl_etat_element_observations": ""
                        }
                    ],
                    "photos": []
                },
                {
                    "edl_etat_element_intitule": "Evier",
                    "edl_etat_element_type": 1,
                    "edl_etat_element_valeur": "",
                    "edl_etat_element_observations": "",
                    "elements": [
                        {
                            "edl_etat_element_intitule": "Nature",
                            "edl_etat_element_type": 2,
                            "edl_etat_element_valeur": "inox",
                            "edl_etat_element_observations": ""
                        }
                    ],
                    "photos": []
                },
                {
                    "edl_etat_element_intitule": "Robinetterie",
                    "edl_etat_element_type": 1,
                    "edl_etat_element_valeur": "",
                    "edl_etat_element_observations": "",
                    "elements": [
                        {
                            "edl_etat_element_intitule": "Description",
                            "edl_etat_element_type": 2,
                            "edl_etat_element_valeur": "mitigeur",
                            "edl_etat_element_observations": ""
                        }
                    ],
                    "photos": []
                },
                {
                    "edl_etat_element_intitule": "Interrupteurs",
                    "edl_etat_element_type": 1,
                    "edl_etat_element_valeur": "",
                    "edl_etat_element_observations": "",
                    "elements": [],
                    "photos": []
                },
                {
                    "edl_etat_element_intitule": "prises",
                    "edl_etat_element_type": 1,
                    "edl_etat_element_valeur": "",
                    "edl_etat_element_observations": "",
                    "elements": [
                        {
                            "edl_etat_element_intitule": "Description",
                            "edl_etat_element_type": 2,
                            "edl_etat_element_valeur": "standard",
                            "edl_etat_element_observations": ""
                        }
                    ],
                    "photos": []
                }
            ]
        },
        {
            "edl_etat_element_intitule": "Chambre",
            "edl_etat_element_type": 1,
            "edl_etat_element_valeur": "",
            "edl_etat_element_observations": "",
            "element": [
                {
                    "edl_etat_element_intitule": "vue g\u00e9n\u00e9rale",
                    "edl_etat_element_type": 1,
                    "edl_etat_element_valeur": "",
                    "edl_etat_element_observations": "",
                    "elements": [],
                    "photos": [
                        {
                            "edl_photo_intitule": "Photo 29, 30",
                            "edl_photo_commentaire": "vue g\u00e9n\u00e9rale",
                            "edl_photo_data_uri": ""
                        }
                    ]
                },
                {
                    "edl_etat_element_intitule": "Sol",
                    "edl_etat_element_type": 1,
                    "edl_etat_element_valeur": "",
                    "edl_etat_element_observations": "",
                    "elements": [
                        {
                            "edl_etat_element_intitule": "Description",
                            "edl_etat_element_type": 2,
                            "edl_etat_element_valeur": "linol\u00e9um",
                            "edl_etat_element_observations": ""
                        },
                        {
                            "edl_etat_element_intitule": "Etat",
                            "edl_etat_element_type": 2,
                            "edl_etat_element_valeur": "d'usage",
                            "edl_etat_element_observations": ""
                        },
                        {
                            "edl_etat_element_intitule": "Description",
                            "edl_etat_element_type": 2,
                            "edl_etat_element_valeur": "Trou (photo 33, 34, 35)\n",
                            "edl_etat_element_observations": ""
                        }
                    ],
                    "photos": [
                        {
                            "edl_photo_intitule": "Photo 31, 32",
                            "edl_photo_commentaire": " Etat d'usage",
                            "edl_photo_data_uri": ""
                        },
                        {
                            "edl_photo_intitule": "Photo 33, 34, 35",
                            "edl_photo_commentaire": " Trou",
                            "edl_photo_data_uri": ""
                        }
                    ]
                },
                {
                    "edl_etat_element_intitule": "Plinthes",
                    "edl_etat_element_type": 1,
                    "edl_etat_element_valeur": "",
                    "edl_etat_element_observations": "",
                    "elements": [
                        {
                            "edl_etat_element_intitule": "Nature",
                            "edl_etat_element_type": 2,
                            "edl_etat_element_valeur": "bois",
                            "edl_etat_element_observations": ""
                        },
                        {
                            "edl_etat_element_intitule": "Etat",
                            "edl_etat_element_type": 2,
                            "edl_etat_element_valeur": "d'usage",
                            "edl_etat_element_observations": ""
                        }
                    ],
                    "photos": [
                        {
                            "edl_photo_intitule": "Photo 36, 37",
                            "edl_photo_commentaire": " Etat d'usage",
                            "edl_photo_data_uri": ""
                        }
                    ]
                },
                {
                    "edl_etat_element_intitule": "Murs",
                    "edl_etat_element_type": 1,
                    "edl_etat_element_valeur": "",
                    "edl_etat_element_observations": "",
                    "elements": [
                        {
                            "edl_etat_element_intitule": "Nature",
                            "edl_etat_element_type": 2,
                            "edl_etat_element_valeur": "cr\u00e9pis",
                            "edl_etat_element_observations": ""
                        },
                        {
                            "edl_etat_element_intitule": "Etat",
                            "edl_etat_element_type": 2,
                            "edl_etat_element_valeur": "d'usage",
                            "edl_etat_element_observations": ""
                        },
                        {
                            "edl_etat_element_intitule": "Description",
                            "edl_etat_element_type": 2,
                            "edl_etat_element_valeur": "Fissure (photo 41, 42, 43)\n",
                            "edl_etat_element_observations": ""
                        }
                    ],
                    "photos": [
                        {
                            "edl_photo_intitule": "Photo 38, 39, 40",
                            "edl_photo_commentaire": " Etat d'usage",
                            "edl_photo_data_uri": ""
                        },
                        {
                            "edl_photo_intitule": "Photo 41, 42, 43",
                            "edl_photo_commentaire": " Fissure",
                            "edl_photo_data_uri": ""
                        }
                    ]
                },
                {
                    "edl_etat_element_intitule": "Radiateur",
                    "edl_etat_element_type": 1,
                    "edl_etat_element_valeur": "",
                    "edl_etat_element_observations": "",
                    "elements": [
                        {
                            "edl_etat_element_intitule": "Description",
                            "edl_etat_element_type": 2,
                            "edl_etat_element_valeur": "\u00e9lectrique",
                            "edl_etat_element_observations": ""
                        },
                        {
                            "edl_etat_element_intitule": "Description",
                            "edl_etat_element_type": 2,
                            "edl_etat_element_valeur": "Impact sur dessus \n",
                            "edl_etat_element_observations": ""
                        },
                        {
                            "edl_etat_element_intitule": "Description",
                            "edl_etat_element_type": 2,
                            "edl_etat_element_valeur": "\u00e0 effectuer par les locataires\n",
                            "edl_etat_element_observations": ""
                        }
                    ],
                    "photos": [
                        {
                            "edl_photo_intitule": "Photo 44",
                            "edl_photo_commentaire": " Impact sur dessus",
                            "edl_photo_data_uri": ""
                        }
                    ]
                },
                {
                    "edl_etat_element_intitule": "Point lumineux",
                    "edl_etat_element_type": 1,
                    "edl_etat_element_valeur": "",
                    "edl_etat_element_observations": "",
                    "elements": [
                        {
                            "edl_etat_element_intitule": "Nature",
                            "edl_etat_element_type": 2,
                            "edl_etat_element_valeur": "douille",
                            "edl_etat_element_observations": ""
                        },
                        {
                            "edl_etat_element_intitule": "Etat",
                            "edl_etat_element_type": 2,
                            "edl_etat_element_valeur": "Bon",
                            "edl_etat_element_observations": ""
                        }
                    ],
                    "photos": [
                        {
                            "edl_photo_intitule": "Photo 45",
                            "edl_photo_commentaire": " Bon \u00e9tat",
                            "edl_photo_data_uri": ""
                        }
                    ]
                },
                {
                    "edl_etat_element_intitule": "Fen\u00eatre",
                    "edl_etat_element_type": 1,
                    "edl_etat_element_valeur": "",
                    "edl_etat_element_observations": "",
                    "elements": [
                        {
                            "edl_etat_element_intitule": "Nature",
                            "edl_etat_element_type": 2,
                            "edl_etat_element_valeur": "bois double",
                            "edl_etat_element_observations": ""
                        },
                        {
                            "edl_etat_element_intitule": "Etat",
                            "edl_etat_element_type": 2,
                            "edl_etat_element_valeur": "Bon",
                            "edl_etat_element_observations": ""
                        }
                    ],
                    "photos": [
                        {
                            "edl_photo_intitule": "Photo 46",
                            "edl_photo_commentaire": " Bon \u00e9tat",
                            "edl_photo_data_uri": ""
                        }
                    ]
                },
                {
                    "edl_etat_element_intitule": "Plafond",
                    "edl_etat_element_type": 1,
                    "edl_etat_element_valeur": "",
                    "edl_etat_element_observations": "",
                    "elements": [
                        {
                            "edl_etat_element_intitule": "Nature",
                            "edl_etat_element_type": 2,
                            "edl_etat_element_valeur": "cr\u00e9pi",
                            "edl_etat_element_observations": ""
                        }
                    ],
                    "photos": []
                },
                {
                    "edl_etat_element_intitule": "Interrupteurs",
                    "edl_etat_element_type": 1,
                    "edl_etat_element_valeur": "",
                    "edl_etat_element_observations": "",
                    "elements": [],
                    "photos": []
                },
                {
                    "edl_etat_element_intitule": "prises",
                    "edl_etat_element_type": 1,
                    "edl_etat_element_valeur": "",
                    "edl_etat_element_observations": "",
                    "elements": [
                        {
                            "edl_etat_element_intitule": "Description",
                            "edl_etat_element_type": 2,
                            "edl_etat_element_valeur": "standard",
                            "edl_etat_element_observations": ""
                        }
                    ],
                    "photos": []
                }
            ]
        },
        {
            "edl_etat_element_intitule": "Salle de bains",
            "edl_etat_element_type": 1,
            "edl_etat_element_valeur": "",
            "edl_etat_element_observations": "",
            "element": [
                {
                    "edl_etat_element_intitule": "vue g\u00e9n\u00e9rale",
                    "edl_etat_element_type": 1,
                    "edl_etat_element_valeur": "",
                    "edl_etat_element_observations": "",
                    "elements": [],
                    "photos": [
                        {
                            "edl_photo_intitule": "Photo 47, 48",
                            "edl_photo_commentaire": "vue g\u00e9n\u00e9rale",
                            "edl_photo_data_uri": ""
                        }
                    ]
                },
                {
                    "edl_etat_element_intitule": "Radiateur",
                    "edl_etat_element_type": 1,
                    "edl_etat_element_valeur": "",
                    "edl_etat_element_observations": "",
                    "elements": [
                        {
                            "edl_etat_element_intitule": "Description",
                            "edl_etat_element_type": 2,
                            "edl_etat_element_valeur": "\u00e9lectrique",
                            "edl_etat_element_observations": ""
                        },
                        {
                            "edl_etat_element_intitule": "Etat",
                            "edl_etat_element_type": 2,
                            "edl_etat_element_valeur": "Bon",
                            "edl_etat_element_observations": ""
                        }
                    ],
                    "photos": [
                        {
                            "edl_photo_intitule": "Photo 49",
                            "edl_photo_commentaire": " Bon \u00e9tat",
                            "edl_photo_data_uri": ""
                        }
                    ]
                },
                {
                    "edl_etat_element_intitule": "Point lumineux",
                    "edl_etat_element_type": 1,
                    "edl_etat_element_valeur": "",
                    "edl_etat_element_observations": "",
                    "elements": [
                        {
                            "edl_etat_element_intitule": "Nature",
                            "edl_etat_element_type": 2,
                            "edl_etat_element_valeur": "douille",
                            "edl_etat_element_observations": ""
                        },
                        {
                            "edl_etat_element_intitule": "Etat",
                            "edl_etat_element_type": 2,
                            "edl_etat_element_valeur": "Bon",
                            "edl_etat_element_observations": ""
                        }
                    ],
                    "photos": [
                        {
                            "edl_photo_intitule": "Photo 50",
                            "edl_photo_commentaire": " Bon \u00e9tat",
                            "edl_photo_data_uri": ""
                        }
                    ]
                },
                {
                    "edl_etat_element_intitule": "Baignoire",
                    "edl_etat_element_type": 1,
                    "edl_etat_element_valeur": "",
                    "edl_etat_element_observations": "",
                    "elements": [
                        {
                            "edl_etat_element_intitule": "Description",
                            "edl_etat_element_type": 2,
                            "edl_etat_element_valeur": "droite",
                            "edl_etat_element_observations": ""
                        },
                        {
                            "edl_etat_element_intitule": "Etat",
                            "edl_etat_element_type": 2,
                            "edl_etat_element_valeur": "Bon",
                            "edl_etat_element_observations": ""
                        }
                    ],
                    "photos": [
                        {
                            "edl_photo_intitule": "Photo 51, 52",
                            "edl_photo_commentaire": " Bon \u00e9tat",
                            "edl_photo_data_uri": ""
                        }
                    ]
                }
            ]
        },
        {
            "edl_etat_element_intitule": "WC",
            "edl_etat_element_type": 1,
            "edl_etat_element_valeur": "",
            "edl_etat_element_observations": "",
            "element": [
                {
                    "edl_etat_element_intitule": "Lavabo",
                    "edl_etat_element_type": 1,
                    "edl_etat_element_valeur": "",
                    "edl_etat_element_observations": "",
                    "elements": [
                        {
                            "edl_etat_element_intitule": "Description",
                            "edl_etat_element_type": 2,
                            "edl_etat_element_valeur": "simple",
                            "edl_etat_element_observations": ""
                        },
                        {
                            "edl_etat_element_intitule": "Etat",
                            "edl_etat_element_type": 2,
                            "edl_etat_element_valeur": "Bon",
                            "edl_etat_element_observations": ""
                        },
                        {
                            "edl_etat_element_intitule": "Description",
                            "edl_etat_element_type": 2,
                            "edl_etat_element_valeur": "Accessoires (crochets ):\n",
                            "edl_etat_element_observations": ""
                        },
                        {
                            "edl_etat_element_intitule": "Etat",
                            "edl_etat_element_type": 2,
                            "edl_etat_element_valeur": "Bon",
                            "edl_etat_element_observations": ""
                        }
                    ],
                    "photos": [
                        {
                            "edl_photo_intitule": "Photo 54",
                            "edl_photo_commentaire": " Bon \u00e9tat",
                            "edl_photo_data_uri": ""
                        },
                        {
                            "edl_photo_intitule": "Photo 55, 56, 57",
                            "edl_photo_commentaire": " Bon \u00e9tat",
                            "edl_photo_data_uri": ""
                        }
                    ]
                },
                {
                    "edl_etat_element_intitule": "Meubles",
                    "edl_etat_element_type": 1,
                    "edl_etat_element_valeur": "",
                    "edl_etat_element_observations": "",
                    "elements": [
                        {
                            "edl_etat_element_intitule": "Description",
                            "edl_etat_element_type": 2,
                            "edl_etat_element_valeur": "stratifi\u00e9s",
                            "edl_etat_element_observations": ""
                        },
                        {
                            "edl_etat_element_intitule": "Etat",
                            "edl_etat_element_type": 2,
                            "edl_etat_element_valeur": "Bon",
                            "edl_etat_element_observations": ""
                        }
                    ],
                    "photos": [
                        {
                            "edl_photo_intitule": "Photo 58, 59",
                            "edl_photo_commentaire": " Bon \u00e9tat",
                            "edl_photo_data_uri": ""
                        }
                    ]
                },
                {
                    "edl_etat_element_intitule": "Porte",
                    "edl_etat_element_type": 1,
                    "edl_etat_element_valeur": "",
                    "edl_etat_element_observations": "",
                    "elements": [
                        {
                            "edl_etat_element_intitule": "Nature",
                            "edl_etat_element_type": 2,
                            "edl_etat_element_valeur": "bois",
                            "edl_etat_element_observations": ""
                        },
                        {
                            "edl_etat_element_intitule": "Etat",
                            "edl_etat_element_type": 2,
                            "edl_etat_element_valeur": "d'usage",
                            "edl_etat_element_observations": ""
                        }
                    ],
                    "photos": [
                        {
                            "edl_photo_intitule": "Photo 60",
                            "edl_photo_commentaire": " Etat d'usage",
                            "edl_photo_data_uri": ""
                        }
                    ]
                },
                {
                    "edl_etat_element_intitule": "Sol",
                    "edl_etat_element_type": 1,
                    "edl_etat_element_valeur": "",
                    "edl_etat_element_observations": "",
                    "elements": [
                        {
                            "edl_etat_element_intitule": "Nature",
                            "edl_etat_element_type": 2,
                            "edl_etat_element_valeur": "carrelage",
                            "edl_etat_element_observations": ""
                        }
                    ],
                    "photos": []
                },
                {
                    "edl_etat_element_intitule": "Murs",
                    "edl_etat_element_type": 1,
                    "edl_etat_element_valeur": "",
                    "edl_etat_element_observations": "",
                    "elements": [
                        {
                            "edl_etat_element_intitule": "Nature",
                            "edl_etat_element_type": 2,
                            "edl_etat_element_valeur": "carrelage",
                            "edl_etat_element_observations": ""
                        }
                    ],
                    "photos": []
                },
                {
                    "edl_etat_element_intitule": "Plafond",
                    "edl_etat_element_type": 1,
                    "edl_etat_element_valeur": "",
                    "edl_etat_element_observations": "",
                    "elements": [
                        {
                            "edl_etat_element_intitule": "Nature",
                            "edl_etat_element_type": 2,
                            "edl_etat_element_valeur": "cr\u00e9pi",
                            "edl_etat_element_observations": ""
                        }
                    ],
                    "photos": []
                },
                {
                    "edl_etat_element_intitule": "Robinetterie",
                    "edl_etat_element_type": 1,
                    "edl_etat_element_valeur": "",
                    "edl_etat_element_observations": "",
                    "elements": [
                        {
                            "edl_etat_element_intitule": "Description",
                            "edl_etat_element_type": 2,
                            "edl_etat_element_valeur": "mitigeur",
                            "edl_etat_element_observations": ""
                        }
                    ],
                    "photos": []
                },
                {
                    "edl_etat_element_intitule": "Ventilation",
                    "edl_etat_element_type": 1,
                    "edl_etat_element_valeur": "",
                    "edl_etat_element_observations": "",
                    "elements": [
                        {
                            "edl_etat_element_intitule": "Description",
                            "edl_etat_element_type": 2,
                            "edl_etat_element_valeur": "automatique",
                            "edl_etat_element_observations": ""
                        }
                    ],
                    "photos": []
                },
                {
                    "edl_etat_element_intitule": "Interrupteurs",
                    "edl_etat_element_type": 1,
                    "edl_etat_element_valeur": "",
                    "edl_etat_element_observations": "",
                    "elements": [],
                    "photos": []
                },
                {
                    "edl_etat_element_intitule": "prises",
                    "edl_etat_element_type": 1,
                    "edl_etat_element_valeur": "",
                    "edl_etat_element_observations": "",
                    "elements": [
                        {
                            "edl_etat_element_intitule": "Description",
                            "edl_etat_element_type": 2,
                            "edl_etat_element_valeur": "standard",
                            "edl_etat_element_observations": ""
                        }
                    ],
                    "photos": []
                }
            ]
        },
        {
            "edl_etat_element_intitule": "Nettoyage + divers",
            "edl_etat_element_type": 1,
            "edl_etat_element_valeur": "",
            "edl_etat_element_observations": "",
            "element": []
        }
    ]
}